store/__init__.py
store/artifact/__init__.py
store/artifact/webhdfs_artifact_repo.py
mlflow_webhdfs-0.0.1.dist-info/LICENSE
mlflow_webhdfs-0.0.1.dist-info/METADATA
mlflow_webhdfs-0.0.1.dist-info/WHEEL
mlflow_webhdfs-0.0.1.dist-info/entry_points.txt
mlflow_webhdfs-0.0.1.dist-info/top_level.txt
mlflow_webhdfs-0.0.1.dist-info/RECORD
