Metadata-Version: 2.2
Name: mlflow-webhdfs
Version: 0.0.1
Summary: MLflow WebHDFS Plugins
Home-page: https://github.com/roach231428/mlflow-webhdfs
Author: roach231428
Author-email: roach231428@gmail.com
License: Apache License 2.0
License-File: LICENSE
Requires-Dist: mlflow
Requires-Dist: hdfs
Dynamic: author
Dynamic: author-email
Dynamic: description
Dynamic: description-content-type
Dynamic: home-page
Dynamic: license
Dynamic: requires-dist
Dynamic: summary
